README.md
setup.py
django_rtk_password/__init__.py
django_rtk_password/admin.py
django_rtk_password/apps.py
django_rtk_password/backends.py
django_rtk_password/models.py
django_rtk_password/validators.py
django_rtk_password.egg-info/PKG-INFO
django_rtk_password.egg-info/SOURCES.txt
django_rtk_password.egg-info/dependency_links.txt
django_rtk_password.egg-info/not-zip-safe
django_rtk_password.egg-info/requires.txt
django_rtk_password.egg-info/top_level.txt
django_rtk_password/migrations/0001_initial.py
django_rtk_password/migrations/__init__.py
django_rtk_password/mutations/__init__.py
django_rtk_password/mutations/changepassword.py
django_rtk_password/mutations/requestpasswordreset.py
django_rtk_password/mutations/resetpassword.py
django_rtk_password/queries/__init__.py
django_rtk_password/tests/__init__.py
django_rtk_password/tests/mutations.py
django_rtk_password/tests/test_schema.py