Metadata-Version: 2.1
Name: django-rtk-password
Version: 0.4.0
Summary: Extension of django-rtk that implements password reset
Home-page: https://github.com/mnieber/django-rtk-home/blob/main/django-rtk-password/README.md
Author: Maarten Nieber
Author-email: hallomaarten@yahoo.com
License: MIT
Platform: UNKNOWN
Requires-Python: >=3.6
